open_agent/__init__.py
open_agent/client.py
open_agent/config.py
open_agent/context.py
open_agent/hooks.py
open_agent/tools.py
open_agent/types.py
open_agent/utils.py
open_agent_sdk-0.4.2.dist-info/licenses/LICENSE
open_agent_sdk-0.4.2.dist-info/METADATA
open_agent_sdk-0.4.2.dist-info/WHEEL
open_agent_sdk-0.4.2.dist-info/top_level.txt
open_agent_sdk-0.4.2.dist-info/RECORD
