Metadata-Version: 2.4
Name: open-agent-sdk
Version: 0.4.2
Summary: Lightweight Python SDK for local/self-hosted LLMs via OpenAI-compatible endpoints
Author: Open Agent SDK Contributors
License: MIT
Project-URL: Homepage, https://github.com/slb350/open-agent-sdk
Project-URL: Repository, https://github.com/slb350/open-agent-sdk
Project-URL: Documentation, https://github.com/slb350/open-agent-sdk/tree/main/docs
Project-URL: Issues, https://github.com/slb350/open-agent-sdk/issues
Keywords: llm,ai,agent,local,openai,ollama,lmstudio,llamacpp
Classifier: Development Status :: 3 - Alpha
Classifier: Intended Audience :: Developers
Classifier: License :: OSI Approved :: MIT License
Classifier: Programming Language :: Python :: 3
Classifier: Programming Language :: Python :: 3.10
Classifier: Programming Language :: Python :: 3.11
Classifier: Programming Language :: Python :: 3.12
Classifier: Programming Language :: Python :: 3.13
Classifier: Topic :: Software Development :: Libraries :: Python Modules
Classifier: Topic :: Scientific/Engineering :: Artificial Intelligence
Requires-Python: >=3.10
License-File: LICENSE
Requires-Dist: openai>=1.0.0
Provides-Extra: yaml
Requires-Dist: pyyaml>=6.0; extra == "yaml"
Provides-Extra: context
Requires-Dist: tiktoken>=0.5.0; extra == "context"
Provides-Extra: dev
Requires-Dist: pytest>=7.0.0; extra == "dev"
Requires-Dist: pytest-asyncio>=0.21.0; extra == "dev"
Requires-Dist: black>=23.0.0; extra == "dev"
Requires-Dist: ruff>=0.1.0; extra == "dev"
Requires-Dist: pyyaml>=6.0; extra == "dev"
Requires-Dist: tiktoken>=0.5.0; extra == "dev"
Dynamic: license-file
